RotEx/__init__.py
RotEx/attitude.py
RotEx/rotate_vectors.py
RotEx/rotex.py
RotEx/utils.py
RotEx-0.2.0.dist-info/LICENSE
RotEx-0.2.0.dist-info/METADATA
RotEx-0.2.0.dist-info/WHEEL
RotEx-0.2.0.dist-info/top_level.txt
RotEx-0.2.0.dist-info/RECORD
