Metadata-Version: 2.1
Name: RotEx
Version: 0.2.0
Summary: RotEx is a set of python helper functions to apply 3D rotation, especially Euler Angles, based on scipy.spatial.transform.Rotation
Home-page: https://github.com/dinglezhang/RotEx
Author: dingle
Author-email: zhangdingh_2004@hotmail.com
Keywords: euler-angles,attitude,rotation,3d-rotation,rotation-extension,rotation-help
Classifier: Development Status :: 4 - Beta
Classifier: Intended Audience :: Developers
Classifier: Programming Language :: Python :: 3
Classifier: Operating System :: OS Independent
Classifier: License :: OSI Approved :: MIT License
License-File: LICENSE
Requires-Dist: scipy
Provides-Extra: dev
Requires-Dist: pytest ; extra == 'dev'
